pygments_style_tomorrownightbright-0.2.dist-info/DESCRIPTION.rst
pygments_style_tomorrownightbright-0.2.dist-info/RECORD
pygments_style_tomorrownightbright-0.2.dist-info/metadata.json
pygments_style_tomorrownightbright-0.2.dist-info/METADATA
pygments_style_tomorrownightbright-0.2.dist-info/WHEEL
pygments_style_tomorrownightbright-0.2.dist-info/entry_points.txt
pygments_style_tomorrownightbright-0.2.dist-info/top_level.txt
pygments_style_tomorrownightbright/__init__.py
pygments_style_tomorrownightbright/tomorrownightbright.py
