Metadata-Version: 2.0
Name: pygments-style-tomorrownightbright
Version: 0.2
Summary: Pygments version of the Tomorrow (night bright) theme.
Home-page: https://github.com/gbraad/pygments-style-tomorrownightbright
Author: Gerard Braad
Author-email: me@gbraad.nl
License: MIT
Keywords: pygments,style,tomorrow,syntax highlighting
Platform: UNKNOWN
Classifier: Development Status :: 4 - Beta
Classifier: Environment :: Plugins
Classifier: Intended Audience :: Developers
Classifier: License :: OSI Approved :: MIT License
Classifier: Operating System :: OS Independent
Classifier: Programming Language :: Python
Classifier: Programming Language :: Python :: 2
Classifier: Topic :: Software Development :: Libraries :: Python Modules
Requires-Dist: pygments (>=1.5)
